transactron/__init__.py
transactron/graph.py
transactron/profiler.py
transactron/tracing.py
transactron/cmd/__init__.py
transactron/cmd/tprof.py
transactron/core/__init__.py
transactron/core/body.py
transactron/core/context.py
transactron/core/keys.py
transactron/core/manager.py
transactron/core/method.py
transactron/core/schedulers.py
transactron/core/sugar.py
transactron/core/tmodule.py
transactron/core/transaction.py
transactron/core/transaction_base.py
transactron/lib/__init__.py
transactron/lib/adapters.py
transactron/lib/allocators.py
transactron/lib/basicio.py
transactron/lib/connectors.py
transactron/lib/dependencies.py
transactron/lib/fifo.py
transactron/lib/logging.py
transactron/lib/metrics.py
transactron/lib/reqres.py
transactron/lib/simultaneous.py
transactron/lib/stack.py
transactron/lib/storage.py
transactron/lib/transformers.py
transactron/testing/__init__.py
transactron/testing/functions.py
transactron/testing/infrastructure.py
transactron/testing/input_generation.py
transactron/testing/logging.py
transactron/testing/method_mock.py
transactron/testing/profiler.py
transactron/testing/test_circuit.py
transactron/testing/testbenchio.py
transactron/testing/tick_count.py
transactron/utils/__init__.py
transactron/utils/assign.py
transactron/utils/data_repr.py
transactron/utils/debug_signals.py
transactron/utils/depcache.py
transactron/utils/dependencies.py
transactron/utils/gen.py
transactron/utils/gen_hacks.py
transactron/utils/idgen.py
transactron/utils/transactron_helpers.py
transactron/utils/typing.py
transactron/utils/amaranth_ext/__init__.py
transactron/utils/amaranth_ext/coding.py
transactron/utils/amaranth_ext/component_interface.py
transactron/utils/amaranth_ext/elaboratables.py
transactron/utils/amaranth_ext/functions.py
transactron/utils/amaranth_ext/memory.py
transactron/utils/amaranth_ext/shifter.py
transactron-0.4.0.dist-info/licenses/LICENSE
transactron-0.4.0.dist-info/METADATA
transactron-0.4.0.dist-info/WHEEL
transactron-0.4.0.dist-info/entry_points.txt
transactron-0.4.0.dist-info/top_level.txt
transactron-0.4.0.dist-info/RECORD
